Workbook

Sheet PROYECCION
B2: ANEXO 3. PROYECCIÓN ECONÓMICA - SOSTENIBILIDAD CORREGIMIENTO LA BUITRERA
B5: Informe de sostenibilidad - Proyección a 5 años
C7: Año 0 ** | D7: Año 1 | E7: Año 2 | F7: Año 3 | G7: Año 4 | H7: Año 5
B8: Fuentes de financiación | C8: =+C15 -> 4.0133592e+08 | D8: =+D15 -> 1.689736e+08 | E8: =+E15 -> 1.6905616e+08 | F8: =+F15 -> 1.7100811e+08 | G8: =+G15 -> 1.7296462e+08 | H8: =+H15 -> 1.7511309e+08
B9: Total Ingresos | C9: =+C8 -> 4.0133592e+08 | D9: =+D8 -> 1.689736e+08 | E9: =+E8 -> 1.6905616e+08 | F9: =+F8 -> 1.7100811e+08 | G9: =+G8 -> 1.7296462e+08 | H9: =+H8 -> 1.7511309e+08
B10: Personal | C10: =+PERSONAL!P4+PERSONAL!P6+PERSONAL!P7+PERSONAL!P8+PERSONAL!P9+PERSONAL!P10+C25 -> 3.2595422e+08 | D10: =+(PERSONAL!F11+PERSONAL!G11+PERSONAL!F12+PERSONAL!F12+PERSONAL!F13+PERSONAL!G13+D25)*(1+D$20) -> 1.3565179e+08 | E10: =+(PERSONAL!H11+PERSONAL!I11+PERSONAL!H12+PERSONAL!I12+PERSONAL!H13+PERSONAL!I13+E25)*(1+E$20) -> 1.3540159e+08 | F10: =+(PERSONAL!J11+PERSONAL!K11+PERSONAL!J12+PERSONAL!K12+PERSONAL!J13+PERSONAL!K13+F25)*(1+F$20) -> 1.3557706e+08 | G10: =+(PERSONAL!L11+PERSONAL!M11+PERSONAL!L12+PERSONAL!M12+PERSONAL!L13+PERSONAL!M13+G25)*(1+G$20) -> 1.3575357e+08 | H10: =+(PERSONAL!N11+PERSONAL!O11+PERSONAL!N12+PERSONAL!O12+PERSONAL!N13+PERSONAL!O13+H25)*(1+H$20) -> 1.3608096e+08
B11: Equipos | C11: =+EQUIPOS!B15 -> 49588420 | D11: =+EQUIPOS!C14*(1+D20) -> 15716935 | E11: =+D11*(1+E20) -> 16314178 | F11: =+E11*(1+F20) -> 16917803 | G11: =+F11*(1+G20) -> 17526844 | H11: =+G11*(1+H20) -> 18157810
B12: Servicios de mantenimiento | C12: =+SERVICIOS!B12 -> 6682048.9 | D12: =+SERVICIOS!C12*(1+D20) -> 9558512.9 | E12: =+SERVICIOS!D12*(1+E20) -> 9290100 | F12: =+SERVICIOS!E12*(1+F20) -> 10370000 | G12: =+SERVICIOS!F12*(1+G20) -> 11447800 | H12: =+SERVICIOS!G12*(1+H20) -> 12535600
B13: Costo de administración - 10%
B14: Imprevistos 5% | C14: =SUM(C10:C13)*5% -> 19111234 | D14: =SUM(D10:D13)*5% -> 8046361.9 | E14: =SUM(E10:E13)*5% -> 8050293.5 | F14: =SUM(F10:F13)*5% -> 8143243.2 | G14: =SUM(G10:G13)*5% -> 8236410.5 | H14: =SUM(H10:H13)*5% -> 8338718.6
B15: Total Costos y Gastos | C15: =SUM(C10:C14) -> 4.0133592e+08 | D15: =SUM(D10:D14) -> 1.689736e+08 | E15: =SUM(E10:E14) -> 1.6905616e+08 | F15: =SUM(F10:F14) -> 1.7100811e+08 | G15: =SUM(G10:G14) -> 1.7296462e+08 | H15: =SUM(H10:H14) -> 1.7511309e+08
B16: ** Para el año 0, se toman cifras del mercado en 2025.
B19: Parametros de crecimiento | C19: Año 0 ** | D19: Año 1 | E19: Año 2 | F19: Año 3 | G19: Año 4 | H19: Año 5
B20: IPC | C20: 0.051 | D20: 0.041 | E20: 0.038 | F20: 0.037 | G20: 0.036 | H20: 0.036
B25: Costo de administración - 10% | C25: 34747699 | D25: 17827357 | E25: 17962933 | F25: 18257933 | G25: 18554501 | H25: 18870519
B36: Informe de sostenibilidad de bancolombia
B37: https://www.bancolombia.com/wcm/connect/www.bancolombia.com-26918/91fc28e2-a303-42e2-98e8-b647309c891d/Gu%E2%94%9C%C2%A1a+Bancolombia+2026+%28Perspectivas+econ%E2%94%9C%E2%94%82micas+OK%29.pdf?MOD=AJPERES&CVID=pCniRMR

Sheet FUENTES DE FINANCIACIÓN
B4: Fuente de financiación | C4: Naturaleza del aporte | D4: Participación (%)
B5: Instituciones territoriales | C5: Monetaria | D5: 0.35
B6: Autoridad ambiental regional | C6: Monetaria | D6: 0.25
B7: Instituciones de educación superior | C7: No monetaria | D7: 0.1
B8: Cooperación Nacional e Internacional | C8: Monetaria | D8: 0.15
B9: Ingresos propios del OAB | C9: Monetaria | D9: 0.1
B10: Comunidad organizada | C10: No monetaria | D10: 0.05
D11: =SUM(D5:D10) -> 1

Sheet PERSONAL
B3: Etapa | C3: Perfil | D3: S1 | E3: S2 | F3: S3 | G3: S4 | H3: S5 | I3: S6 | J3: S7 | K3: S8 | L3: S9 | M3: S10 | N3: S11 | O3: S12 | P3: Total
B4: Desarrollo | C4: Coordinador Equipo Técnico | D4: =6417000*6 -> 38502000 | E4: =6417000*6 -> 38502000 | P4: =SUM(D4:O4) -> 77004000
C5: Desarrollador SIG Full Stack | D5: =5346000*6 -> 32076000 | E5: =5346000*6 -> 32076000 | P5: =SUM(D5:O5) -> 64152000
C6: Diseñador Web / UX | D6: =4197480*6 -> 25184880 | E6: =4197480*6 -> 25184880 | P6: =SUM(D6:O6) -> 50369760
C7: Administrador del Sistema | D7: =4197480*6 -> 25184880 | E7: =4197480*6 -> 25184880 | P7: =SUM(D7:O7) -> 50369760
C8: Auxiliar Apoyo Operativo | D8: =2241000*6 -> 13446000 | E8: =2241000*6 -> 13446000 | P8: =SUM(D8:O8) -> 26892000
C9: Técnico en Integración IoT | E9: =3736500*6 -> 22419000 | P9: =SUM(D9:O9) -> 22419000
C10: Desarrollador Móvil Multiplataforma | D10: =5346000*6 -> 32076000 | E10: =5346000*6 -> 32076000 | P10: =SUM(D10:O10) -> 64152000
B11: Operación y Mantenimiento | C11: Administrador del Sistema | F11: =4197480*6 -> 25184880 | G11: =4197480*6 -> 25184880 | H11: =4197480*6 -> 25184880 | I11: =4197480*6 -> 25184880 | J11: =4197480*6 -> 25184880 | K11: =4197480*6 -> 25184880 | L11: =4197480*6 -> 25184880 | M11: =4197480*6 -> 25184880 | ... O11: =4197480*6 -> 25184880 | P11: =SUM(D11:O11) -> 251848800
C12: Técnico de Soporte | F12: =2935000*6 -> 17610000 | G12: =2935000*6 -> 17610000 | H12: =2935000*6 -> 17610000 | I12: =2935000*6 -> 17610000 | J12: =2935000*6 -> 17610000 | K12: =2935000*6 -> 17610000 | L12: =2935000*6 -> 17610000 | M12: =2935000*6 -> 17610000 | ... O12: =2935000*6 -> 17610000 | P12: =SUM(D12:O12) -> 176100000
C13: Auxiliar Apoyo Operativo | F13: =2241000*6 -> 13446000 | G13: =2241000*6 -> 13446000 | H13: =2241000*6 -> 13446000 | I13: =2241000*6 -> 13446000 | J13: =2241000*6 -> 13446000 | K13: =2241000*6 -> 13446000 | L13: =2241000*6 -> 13446000 | M13: =2241000*6 -> 13446000 | ... O13: =2241000*6 -> 13446000 | P13: =SUM(D13:O13) -> 134460000
B15: Cargo | C15: Coordinador equipo técnico
B16: Perfil | C16: Profesional en Ingeniería Ambiental, Urbanismo, Geografía, Topografía, Geodesia, Catastro, SIG u afines. Con posgrado en Geomática, SIG o áreas relacionadas
B17: Experiencia | C17: • Mínimo 5 años de experiencia laboral. • Mínimo 3 años de experiencia específica en Sistemas de Información Geográfica.
B19: Cargo | C19: Desarrollador SIG
B20: Perfil | C20: Profesional en Ingeniería de Sistemas, Ingeniería Topográfica o afines, con posgrado o experiencia de más de 5 años en desarrollo web, SIG o sistemas de información.
B21: Experiencia | C21: Mínimo cinco años de experiencia profesional en desarrollo de software y soluciones SIG.
B23: Cargo | C23: Profesional diseño web
B24: Perfil | C24: Profesional en diseño gráfico, comunicación digital, diseño web, producción de medios o áreas afines.
B25: Experiencia | C25: Mínimo un año de experiencia en diseño web, UI/UX o diseño digital aplicado a plataformas interactivas.
B27: Cargo | C27: Auxiliar apoyo operativo
B28: Perfil | C28: Tecnólogo o estudiante de Ingeniería de Sistemas, Desarrollo de Software o carreras afines. También se acepta experiencia equivalente adquirida en formación técnica o proyectos previos.
B29: Experiencia | C29: Ideal para estudiante en etapa de pasantía, prácticas o primeros semestres de experiencia profesional.
... B44: Perfil | C44: Profesional en ingeniería de sistemas, ciencias de la computación o áreas afines. - Dominio de al menos un framework multiplataforma moderno (Flutter, React Native). - Conocimientos en arquitectura de aplicaciones móviles y patrones de diseño. - Manejo de herramientas de control de versiones (Git).
C45: 2 a 4 años desarrollando apps móviles en producción. Experiencia integrando servicios REST, autenticación y manejo de estados. Deseable experiencia previa con módulos de mapas (Leaflet).

Sheet EQUIPOS
B2: Año 0 ** | C2: Año 1 | D2: Año 2 | E2: Año 3 | F2: Año 4 | G2: Año 5
A3: Servidores / cloud / dominio
A4: Servidor principal | B4: 18266500
B5: =SUM(B4) -> 18266500 | C5: =SUM(C4) -> 0 | D5: =SUM(D4) -> 0 | E5: =SUM(E4) -> 0 | F5: =SUM(F4) -> 0 | G5: =SUM(G4) -> 0
A6: Equipos de usuarios
A7: PCs - 3 Portatiles | B7: 13209000
A8: Móviles - 3 | B8: =1000000*3 -> 3000000
B9: =SUM(B7:B8) -> 16209000 | C9: =SUM(C7:C8) -> 0 | D9: =SUM(D7:D8) -> 0 | E9: =SUM(E7:E8) -> 0 | F9: =SUM(F7:F8) -> 0 | G9: =SUM(G7:G8) -> 0
A10: Infraestructura IoT
A11: Kit Estación meteorologica + sensores + paneles solares | B11: =(13424000+(13424000*8%)) -> 14497920 | C11: 14497920 | D11: 14497920 | E11: 14497920 | F11: 14497920 | G11: 14497920
A12: Conectividad SIM/datos | B12: =15000+(50000*12) -> 615000 | C12: =50000*12 -> 600000 | D12: =50000*12 -> 600000 | E12: =50000*12 -> 600000 | F12: =50000*12 -> 600000 | G12: =50000*12 -> 600000
B14: =SUM(B11:B13) -> 15112920 | C14: =SUM(C11:C13) -> 15097920 | D14: =SUM(D11:D13) -> 15097920 | E14: =SUM(E11:E13) -> 15097920 | F14: =SUM(F11:F13) -> 15097920 | G14: =SUM(G11:G13) -> 15097920
B15: =SUM(B5+B9+B14) -> 49588420 | C15: =SUM(C5+C9+C14) -> 15097920 | D15: =SUM(D5+D9+D14) -> 15097920 | E15: =SUM(E5+E9+E14) -> 15097920 | F15: =SUM(F5+F9+F14) -> 15097920 | G15: =SUM(G5+G9+G14) -> 15097920
A17: ** Para el año 0, se toman cifras del mercado en 2025.
A21: Kit Estación Meteorológica HOBO U30 NRC | C21: https://colombia.bioweb.co/products/kit-estacion-meteorologica-hobo-u30-nrc?_pos=43&_sid=4857390c3&_ss=r
A22: Registrador de datos HOBO U30 NRC con 10 entradas. Panel Solar 5W. Sensor inteligente de temperatura / HR con cable de 2 metros . Sensor inteligente de velocidad del viento con cable de 3 metros . Sensor inteligente de dirección del viento con cable de 3 metros . Cruceta completa para sensores de velocidad / dirección del viento . Pantalla de radiación solar para sensor de temperatura y HR.
A31: Equipos: servidor, portatiles y servicio de mantenimiento

Sheet SERVICIOS
A2: Mantenimiento Equipos de computo | B2: 400000
A3: Mantenimiento Estación meteologica y sensores | B3: 350000
A4: Mantenimiento infraestructura solar | B4: 700000
A6: Servicios | B6: Año 0 ** | C6: Año 1 | D6: Año 2 | E6: Año 3 | F6: Año 4 | G6: Año 5
A7: Alquiler equipos portatiles | B7: =+((269338+(269338*19%)))*4 -> 1282048.9 | C7: =+((269338+(269338*19%)))*4 -> 1282048.9 | D7: 0 | E7: 0 | F7: 0 | G7: 0
A8: Alquiler servidor nube | B8: 3000000 | C8: 3000000 | D8: 3000000 | E8: 3000000 | F8: 3000000 | G8: 3000000
A9: Internet | B9: =200000*12 -> 2400000 | C9: =200000*12 -> 2400000 | D9: =200000*12 -> 2400000 | E9: =200000*12 -> 2400000 | F9: =200000*12 -> 2400000 | G9: =200000*12 -> 2400000
A10: Licencia - dominio (gov.co) | B10: 0 | C10: 0 | D10: 0 | E10: 0 | F10: 0 | G10: 0
A11: Mantenimiento - Equipos propios | B11: 0 | C11: =+$B$2+($B$3*2)+($B$4*2) -> 2500000 | D11: =+$B$2+($B$3*3)+($B$4*3) -> 3550000 | E11: =+$B$2+($B$3*4)+($B$4*4) -> 4600000 | F11: =+$B$2+($B$3*5)+($B$4*5) -> 5650000 | G11: =+$B$2+($B$3*6)+($B$4*6) -> 6700000
B12: =SUM(B7:B11) -> 6682048.9 | C12: =SUM(C7:C11) -> 9182048.9 | D12: =SUM(D7:D11) -> 8950000 | E12: =SUM(E7:E11) -> 10000000 | F12: =SUM(F7:F11) -> 11050000 | G12: =SUM(G7:G11) -> 12100000
A13: ** Para el año 0, se toman cifras del mercado en 2025.
A20: Alquier equipos portatiles - Gama media
